tree_of_thoughts/__init__.py
tree_of_thoughts/agent.py
tree_of_thoughts/bfs.py
tree_of_thoughts/dfs.py
tree_of_thoughts-0.6.5.dist-info/LICENSE
tree_of_thoughts-0.6.5.dist-info/METADATA
tree_of_thoughts-0.6.5.dist-info/WHEEL
tree_of_thoughts-0.6.5.dist-info/RECORD
