Metadata-Version: 2.1
Name: tree-of-thoughts
Version: 0.6.5
Summary: Tree of Thoughts - Pytorch
Home-page: https://github.com/kyegomez/tree-of-thoughts
License: MIT
Keywords: artificial intelligence,deep learning,optimizers,Prompt Engineering
Author: Kye Gomez
Author-email: kye@apac.ai
Requires-Python: >=3.10,<4.0
Classifier: Development Status :: 4 - Beta
Classifier: Intended Audience :: Developers
Classifier: License :: OSI Approved :: MIT License
Classifier: Programming Language :: Python :: 3
Classifier: Programming Language :: Python :: 3.10
Classifier: Programming Language :: Python :: 3.11
Classifier: Programming Language :: Python :: 3.12
Classifier: Programming Language :: Python :: 3.6
Classifier: Topic :: Scientific/Engineering :: Artificial Intelligence
Requires-Dist: loguru
Requires-Dist: numpy
Requires-Dist: pydantic
Requires-Dist: python-dotenv
Requires-Dist: swarm-models
Requires-Dist: swarms
